Metadata-Version: 2.1
Name: kzas-herepy
Version: 3.5.2
Summary: A library that provides a Python interface to the HERE APIs
Home-page: https://github.com/abdullahselek/HerePy
Author: Abdullah Selek
Author-email: abdullahselek@gmail.com
License: MIT License
Download-URL: https://pypi.org/pypi/herepy
Keywords: here api,here technologies,here python api clients,rest api clients
Platform: Any
Classifier: Intended Audience :: Developers
Classifier: License :: OSI Approved :: MIT License
Classifier: Operating System :: OS Independent
Classifier: Topic :: Software Development :: Libraries :: Python Modules
Classifier: Programming Language :: Python
Classifier: Programming Language :: Python :: 3
Classifier: Programming Language :: Python :: 3.5
Classifier: Programming Language :: Python :: 3.6
Classifier: Programming Language :: Python :: 3.7
Classifier: Programming Language :: Python :: 3.8
Classifier: Programming Language :: Python :: 3.9
Requires-Python: >=3.5
Requires-Dist: requests (==2.25.1)
